setup.py
birdfeeder/__init__.py
birdfeeder/connection.py
birdfeeder/credentials.py
birdfeeder/defaults.py
birdfeeder/main.py
birdfeeder/parsers.py
birdfeeder/streaming.py
birdfeeder/util.py
birdfeeder.egg-info/PKG-INFO
birdfeeder.egg-info/SOURCES.txt
birdfeeder.egg-info/dependency_links.txt
birdfeeder.egg-info/namespace_packages.txt
birdfeeder.egg-info/not-zip-safe
birdfeeder.egg-info/requires.txt
birdfeeder.egg-info/top_level.txt