Metadata-Version: 1.1
Name: birdfeeder
Version: 0.0.9
Summary: A newslynx-opinionated wrapper around twython
Home-page: http://github.com/newslynx/birdfeeder
Author: Brian Abelson
Author-email: brian@newslynx.org
License: MIT
Platform: UNKNOWN
Classifier: Development Status :: 3 - Alpha
Classifier: Intended Audience :: Developers
Classifier: License :: OSI Approved :: MIT License
Classifier: Operating System :: OS Independent
Classifier: Programming Language :: Python
